Metadata-Version: 1.1
Name: flask-contentful
Version: 0.0.1
Summary: UNKNOWN
Home-page: https://github.com/eillarra/flask-contentful
Author: eillarra
Author-email: eneko@illarra.com
License: MIT
Keywords: flask contentful
Platform: UNKNOWN
Classifier: Development Status :: 1 - Planning
Classifier: Environment :: Web Environment
Classifier: Intended Audience :: Developers
Classifier: License :: OSI Approved :: MIT License
Classifier: Operating System :: OS Independent
Classifier: Programming Language :: Python
Classifier: Programming Language :: Python :: 3.6
Classifier: Topic :: Internet :: WWW/HTTP :: Dynamic Content
